richapi/__init__.py
richapi/__version__.py
richapi/cli.py
richapi/exceptions.py
richapi/exc_parser/__init__.py
richapi/exc_parser/compiler.py
richapi/exc_parser/handler.py
richapi/exc_parser/openapi.py
richapi/exc_parser/protocol.py
richapi-0.3.2.dist-info/METADATA
richapi-0.3.2.dist-info/WHEEL
richapi-0.3.2.dist-info/entry_points.txt
richapi-0.3.2.dist-info/RECORD
