Metadata-Version: 2.3
Name: richapi
Version: 0.3.2
Summary: Find HTTPExceptions and turn them into documented responses!
Project-URL: repository, https://github.com/ManiMozaffar/richapi
Project-URL: Homepage, https://github.com/ManiMozaffar/richapi
Project-URL: Documentation, https://github.com/ManiMozaffar/richapi
Project-URL: Source, https://github.com/ManiMozaffar/richapi
License-Expression: MIT
Requires-Python: >=3.9
Requires-Dist: fastapi>=0.105
Requires-Dist: typer>=0.12
